threeza/__init__.py
threeza/conventions.py
threeza/crowd/__init__.py
threeza/crowd/categoricallottery.py
threeza/crowd/ongoingcategoricallottery.py
threeza/inclusion/__init__.py
threeza/inclusion/momentuminclusion.py
threeza/inclusion/numpyinclusion.py
threeza/inclusion/timemachinesinclusion.py
threeza-1.0.3.dist-info/METADATA
threeza-1.0.3.dist-info/WHEEL
threeza-1.0.3.dist-info/entry_points.txt
threeza-1.0.3.dist-info/top_level.txt
threeza-1.0.3.dist-info/RECORD
