Metadata-Version: 2.1
Name: threeza
Version: 1.0.3
Summary: Lottery like mechanisms for crowd-sourcing
Home-page: https://github.com/microprediction/threeza
Author: microprediction
Author-email: peter.cotton@microprediction.com
License: MIT
Platform: UNKNOWN
Classifier: License :: OSI Approved :: MIT License
Classifier: Programming Language :: Python :: 3
Classifier: Programming Language :: Python :: 3.7
Requires-Dist: wheel
Requires-Dist: pathlib
